poetpy/__init__.py
poetpy/api.py
poetpy-1.1.1.dist-info/LICENSE.txt
poetpy-1.1.1.dist-info/METADATA
poetpy-1.1.1.dist-info/WHEEL
poetpy-1.1.1.dist-info/top_level.txt
poetpy-1.1.1.dist-info/RECORD
